time_tracker/utils/DynamoDB.py
time_tracker/utils/__init__.py
time_tracker/utils/cloudwatch_log.py
time_tracker/utils/notifications.py
time_tracker/utils/s3_storage.py
time_tracker/utils/sqs_helper.py
library_utils-0.1.9.dist-info/METADATA
library_utils-0.1.9.dist-info/WHEEL
library_utils-0.1.9.dist-info/top_level.txt
library_utils-0.1.9.dist-info/RECORD
