Metadata-Version: 2.1
Name: library-utils
Version: 0.1.9
Summary: A collection of utility functions for AWS services
Home-page: https://github.com/Jiyoung0716/Final_CPP_Project
Author: x24142816-JiyoungKim
Author-email: x24142816@student.ncirl.ie
License: UNKNOWN
Platform: UNKNOWN
Classifier: Programming Language :: Python :: 3
Classifier: License :: OSI Approved :: MIT License
Classifier: Operating System :: OS Independent
Requires-Python: >=3.6
Requires-Dist: boto3==1.37.8
Requires-Dist: botocore==1.37.8
Requires-Dist: Django==4.2.19
Requires-Dist: setuptools==59.6.0
Requires-Dist: gunicorn==23.0.0
Requires-Dist: Pillow==11.1.0
